{ "ranking": [ { "wc_id": 13907358, "favorite_number": 2, "date_id": 3, "genre_id": 48, "update_id": 135240 }, { "wc_id": 13925669, "favorite_number": 2, "date_id": 3, "genre_id": 48, "update_id": 130932 }, { "wc_id": 13926894, "favorite_number": 1, "date_id": 3, "genre_id": 48, "update_id": 135156 }, { "wc_id": 13917299, "favorite_number": 1, "date_id": 2, "genre_id": 47, "update_id": 121815 }, { "wc_id": 13918052, "favorite_number": 1, "date_id": 3, "genre_id": 48, "update_id": 131064 }, { "wc_id": 13919153, "favorite_number": 1, "date_id": 3, "genre_id": 48, "update_id": 131078 }, { "wc_id": 13919945, "favorite_number": 1, "date_id": 1, "genre_id": 21, "update_id": 108360 }, { "wc_id": 13923358, "favorite_number": 1, "date_id": 3, "genre_id": 48, "update_id": 133928 }, { "wc_id": 13925156, "favorite_number": 1, "date_id": 3, "genre_id": 48, "update_id": 135242 }, { "wc_id": 13926110, "favorite_number": 1, "date_id": 2, "genre_id": 47, "update_id": 122283 }, { "wc_id": 13916501, "favorite_number": 1, "date_id": 3, "genre_id": 6, "update_id": 140092 }, { "wc_id": 13926918, "favorite_number": 1, "date_id": 1, "genre_id": 21, "update_id": 108354 }, { "wc_id": 13928557, "favorite_number": 1, "date_id": 3, "genre_id": 48, "update_id": 131070 }, { "wc_id": 13929360, "favorite_number": 1, "date_id": 3, "genre_id": 48, "update_id": 131022 }, { "wc_id": 13929980, "favorite_number": 1, "date_id": 3, "genre_id": 48, "update_id": 131123 }, { "wc_id": 13932224, "favorite_number": 1, "date_id": 1, "genre_id": 21, "update_id": 108315 }, { "wc_id": 13933599, "favorite_number": 1, "date_id": 1, "genre_id": 21, "update_id": 111977 }, { "wc_id": 13934564, "favorite_number": 1, "date_id": 2, "genre_id": 47, "update_id": 122063 }, { "wc_id": 13937623, "favorite_number": 1, "date_id": 3, "genre_id": 48, "update_id": 132336 }, { "wc_id": 13905450, "favorite_number": 1, "date_id": 1, "genre_id": 21, "update_id": 111268 }, { "wc_id": 13901976, "favorite_number": 1, "date_id": 1, "genre_id": 10, "update_id": 103905 }, { "wc_id": 13902818, "favorite_number": 1, "date_id": 1, "genre_id": 21, "update_id": 111267 }, { "wc_id": 13902997, "favorite_number": 1, "date_id": 3, "genre_id": 48, "update_id": 135126 }, { "wc_id": 13903560, "favorite_number": 1, "date_id": 3, "genre_id": 48, "update_id": 130939 }, { "wc_id": 13903814, "favorite_number": 1, "date_id": 1, "genre_id": 21, "update_id": 112496 }, { "wc_id": 13904159, "favorite_number": 1, "date_id": 3, "genre_id": 48, "update_id": 133917 }, { "wc_id": 13905309, "favorite_number": 1, "date_id": 2, "genre_id": 47, "update_id": 121810 }, { "wc_id": 13905361, "favorite_number": 1, "date_id": 3, "genre_id": 48, "update_id": 135152 }, { "wc_id": 13916656, "favorite_number": 1, "date_id": 1, "genre_id": 21, "update_id": 112097 }, { "wc_id": 13905459, "favorite_number": 1, "date_id": 1, "genre_id": 21, "update_id": 112005 }, { "wc_id": 13907256, "favorite_number": 1, "date_id": 2, "genre_id": 47, "update_id": 122413 }, { "wc_id": 13907796, "favorite_number": 1, "date_id": 1, "genre_id": 21, "update_id": 108340 }, { "wc_id": 13909153, "favorite_number": 1, "date_id": 3, "genre_id": 48, "update_id": 131127 }, { "wc_id": 13910504, "favorite_number": 1, "date_id": 3, "genre_id": 48, "update_id": 134614 }, { "wc_id": 13910520, "favorite_number": 1, "date_id": 2, "genre_id": 47, "update_id": 122287 }, { "wc_id": 13915838, "favorite_number": 1, "date_id": 2, "genre_id": 47, "update_id": 122140 }, { "wc_id": 13901231, "favorite_number": 1, "date_id": 1, "genre_id": 21, "update_id": 111271 } ] }